Metadata-Version: 2.1
Name: whassup-V12.1.2
Version: 12.1.2
Summary: to development a face and emotion recognition system
Home-page: https://github.com/Blacknight-dev/whatsup
Author: Blacknight
Author-email: sunugahn@gmail.com
Classifier: Programming Language :: Python :: 3
Classifier: License :: OSI Approved :: MIT License
Classifier: Operating System :: OS Independent
Requires-Python: >=3.10
Requires-Dist: Django<4.0,>=3.0
Requires-Dist: opencv-python>=4.5.0
Requires-Dist: numpy<2.0.0,>=1.19.0
Requires-Dist: deepface==0.093
